bauxite/__init__.py
bauxite/constants.py
bauxite/contrib/__init__.py
bauxite/error.py
bauxite/gateway/__init__.py
bauxite/gateway/client.py
bauxite/gateway/enums.py
bauxite/gateway/errors.py
bauxite/gateway/ratelimiting.py
bauxite/gateway/shard.py
bauxite/http/__init__.py
bauxite/http/client.py
bauxite/http/errors.py
bauxite/http/file.py
bauxite/http/ratelimiting.py
bauxite/http/route.py
bauxite-1.0.2.dist-info/LICENSE
bauxite-1.0.2.dist-info/WHEEL
bauxite-1.0.2.dist-info/METADATA
bauxite-1.0.2.dist-info/RECORD
