Metadata-Version: 2.1
Name: bauxite
Version: 1.0.2
Summary: A robust, low-level connector for the Discord API
Home-page: https://github.com/vcokltfre/bauxite
License: MIT
Author: vcokltfre
Author-email: vcokltfre@gmail.com
Requires-Python: >=3.9,<4.0
Classifier: Framework :: AsyncIO
Classifier: Intended Audience :: Developers
Classifier: License :: OSI Approved :: MIT License
Classifier: Natural Language :: English
Classifier: Operating System :: OS Independent
Classifier: Programming Language :: Python :: 3
Classifier: Programming Language :: Python :: 3.10
Classifier: Programming Language :: Python :: 3.8
Classifier: Programming Language :: Python :: 3.9
Classifier: Programming Language :: Python :: Implementation :: CPython
Classifier: Topic :: Communications :: Chat
Classifier: Typing :: Typed
Requires-Dist: aiohttp (>=3.8.1,<4.0.0)
Project-URL: Repository, https://github.com/vcokltfre/bauxite
